bili_scraper/__init__.py
bili_scraper/bili_scraper.py
bili_scraper/api_reverse/__init__.py
bili_scraper/api_reverse/article/__init__.py
bili_scraper/api_reverse/article/get_article.py
bili_scraper/api_reverse/video/__init__.py
bili_scraper/api_reverse/video/dm_pb2.py
bili_scraper/api_reverse/video/get_Comments.py
bili_scraper/api_reverse/video/get_video.py
bili_scraper/api_reverse/video/get_video_dm.py
bili_scraper/api_reverse/video/get_w_rid_And_wts.py
bili_scraper-0.1.2.dist-info/licenses/LICENSE
bili_scraper-0.1.2.dist-info/METADATA
bili_scraper-0.1.2.dist-info/WHEEL
bili_scraper-0.1.2.dist-info/top_level.txt
bili_scraper-0.1.2.dist-info/RECORD
