Metadata-Version: 2.4
Name: bili-scraper
Version: 0.1.2
Summary: Bilibili website crawler that can download videos, dm, comments, articles, and more.
Author-email: guoziqi329 <guoziqi329@gmail.com>
License-Expression: MIT
Project-URL: Homepage, https://github.com/Guoziqi329/bili-scraper
Classifier: Programming Language :: Python :: 3
Requires-Python: >=3.8
License-File: LICENSE
Requires-Dist: requests>=2.0
Requires-Dist: python-docx>=1.2.0
Requires-Dist: Pillow>=11.3.0
Requires-Dist: moviepy>=2.1.2
Requires-Dist: protobuf>=6.32.0
Requires-Dist: click
Dynamic: license-file
